{"cameraMode":{"drawMode":0,"name":"Shaded","section":"Shading Mode"},"sceneLighting":true,"audioPlay":false,"sceneViewState":{"m_AlwaysRefresh":false,"showFog":true,"showSkybox":true,"showFlares":true,"showImageEffects":true,"showParticleSystems":true,"showVisualEffectGraphs":true,"m_FxEnabled":true},"in2DMode":false,"pivot":{"x":-9.463375091552735,"y":-18.378559112548829,"z":45.82114791870117},"rotation":{"x":0.19673322141170503,"y":-0.4705520570278168,"z":0.10819956660270691,"w":0.853104293346405},"size":1.1761544942855836,"orthographic":false}